[
  {
    "videoId": "djzKCZHeVjY",
    "title": "Ain&#39;t No Twin Primes (live) | Bill Withers parody by 3Blue1Brown and Acapella Science",
    "publishedAt": "2024-04-21T18:01:02Z",
    "thumbnail": "https://i.ytimg.com/vi/djzKCZHeVjY/default.jpg"
  },

  {
    "videoId": "UOuxo6SA8Uc",
    "title": "Math&#39;s pedagogical curse | Grant Sanderson JPBM Award Lecture, JMM 2023",
    "publishedAt": "2023-04-01T04:13:54Z",
    "thumbnail": "https://i.ytimg.com/vi/UOuxo6SA8Uc/default.jpg"
  },
  {
    "videoId": "gvck7ssg9dE",
    "title": "When do programmatic visuals help in understanding math? 3b1b, SIGGRAPH 2021 Featured Speaker",
    "publishedAt": "2021-10-14T20:17:52Z",
    "thumbnail": "https://i.ytimg.com/vi/gvck7ssg9dE/default.jpg"
  },
  {
    "videoId": "pvRY3r-b0QI",
    "title": "Tai-Danae Bradley: Where math meets language | 3b1b Podcast #5",
    "publishedAt": "2021-09-25T17:50:55Z",
    "thumbnail": "https://i.ytimg.com/vi/pvRY3r-b0QI/default.jpg"
  },
  {
    "videoId": "puXKFn-nKis",
    "title": "Dianna Cowern: From MIT to Physics Girl | 3b1b Podcast #4",
    "publishedAt": "2021-08-31T14:04:41Z",
    "thumbnail": "https://i.ytimg.com/vi/puXKFn-nKis/default.jpg"
  },

  {
    "videoId": "SUMLKweFAYk",
    "title": "Steven Strogatz: In and out of love with math | 3b1b podcast #3",
    "publishedAt": "2021-08-07T22:39:57Z",
    "thumbnail": "https://i.ytimg.com/vi/SUMLKweFAYk/default.jpg"
  }
]
